easyGrapher/__init__.py
easyGrapher-0.0.1.dist-info/LICENSE
easyGrapher-0.0.1.dist-info/METADATA
easyGrapher-0.0.1.dist-info/WHEEL
easyGrapher-0.0.1.dist-info/top_level.txt
easyGrapher-0.0.1.dist-info/RECORD
