Metadata-Version: 2.1
Name: easyGrapher
Version: 0.0.1
Summary: Python graphing package.
Home-page: https://github.com/Password-Classified/easyGrapher
Author: Password-Classified
Author-email: user@example.com
License: UNKNOWN
Project-URL: Bug Tracker, https://github.com/Password-Classified/easyGrapher/issues
Keywords: python,data,visualization,graphs,data vis
Platform: UNKNOWN
Classifier: Development Status :: 1 - Planning
Classifier: Intended Audience :: Developers
Classifier: Programming Language :: Python :: 3
Classifier: Operating System :: Unix
Classifier: Operating System :: MacOS :: MacOS X
Classifier: Operating System :: Microsoft :: Windows
Requires-Python: >=3.6
